{"is_source_file": true, "format": "JavaScript (React JSX)", "description": "This is a React component defining a page called BlocksLibrary, which displays UI blocks with a sidebar for category selection and preview cards for different block types.", "external_files": ["../components/Sidebar", "../components/PreviewCard"], "external_methods": [], "published": [], "classes": [{"name": "BlocksLibrary", "description": "A React functional component for the Blocks Library page, displaying categories and a feature grid."}], "methods": [{"name": "FeatureGrid", "description": "A React component that renders a grid of feature blocks with labels like 'Fast', 'Accessible', and 'Beautiful'."}, {"name": "BlocksLibrary()", "scope": "", "scopeKind": "", "description": "unavailable"}], "calls": ["React", "React.useMemo", "React.useState", "../components/Sidebar", "../components/PreviewCard", "<FeatureGrid />"], "search-terms": ["BlocksLibrary", "FeatureGrid", "Sidebar", "PreviewCard", "ui_blocks", "jsx page component"], "state": 2, "file_id": 21, "knowledge_revision": 47, "git_revision": "", "ctags": [{"_type": "tag", "name": "BlocksLibrary", "path": "/home/kavia/workspace/code-generation/tailwind-ui-clone-1854-1863/ui_library_frontend/src/pages/BlocksLibrary.js", "pattern": "/^export default function BlocksLibrary() {$/", "language": "JavaScript", "kind": "function", "signature": "()"}, {"_type": "tag", "name": "blockCode", "path": "/home/kavia/workspace/code-generation/tailwind-ui-clone-1854-1863/ui_library_frontend/src/pages/BlocksLibrary.js", "pattern": "/^                code={blockCode}$/", "language": "JavaScript", "kind": "field", "scope": "BlocksLibrary.code", "scopeKind": "class"}], "hash": "ddf5152aa4ed3f4a9c020c5eab8ae239", "format-version": 4, "code-base-name": "ui_library_frontend", "filename": "ui_library_frontend/src/pages/BlocksLibrary.js", "fields": [{"name": "code={blockCode}", "scope": "BlocksLibrary.code", "scopeKind": "class", "description": "unavailable"}], "revision_history": [{"47": ""}]}